lowkernels/__init__.py
lowkernels/builder.py
lowkernels/project.py
lowkernels-0.1.1.dist-info/LICENSE
lowkernels-0.1.1.dist-info/METADATA
lowkernels-0.1.1.dist-info/WHEEL
lowkernels-0.1.1.dist-info/top_level.txt
lowkernels-0.1.1.dist-info/RECORD
