Metadata-Version: 2.1
Name: lowkernels
Version: 0.1.1
Summary: A small tool to create low-kernel operating system using C. Learn more at lowkernels.readthedocs.io
Author: lowkernels
License: MIT
License-File: LICENSE
